casepropods.family_connect_registration-2.0.8-py3.6-nspkg.pth
casepropods/family_connect_registration/__init__.py
casepropods/family_connect_registration/plugin.py
casepropods/family_connect_registration/tests.py
casepropods.family_connect_registration-2.0.8.dist-info/LICENSE
casepropods.family_connect_registration-2.0.8.dist-info/METADATA
casepropods.family_connect_registration-2.0.8.dist-info/WHEEL
casepropods.family_connect_registration-2.0.8.dist-info/namespace_packages.txt
casepropods.family_connect_registration-2.0.8.dist-info/top_level.txt
casepropods.family_connect_registration-2.0.8.dist-info/RECORD
