Metadata-Version: 2.1
Name: casepropods.family-connect-registration
Version: 2.0.8
Summary: FamilyConnect registrations data pod for casepro. Returns  case specific registration information.
Home-page: http://github.com/praekelt/casepro.pods.familyconnect
Author: Praekelt Foundation
Author-email: dev@praekelt.com
License: BSD
Platform: UNKNOWN
Classifier: Programming Language :: Python
Classifier: Framework :: Django
Classifier: Topic :: Internet :: WWW/HTTP
Classifier: Topic :: Internet :: WWW/HTTP :: WSGI :: Application
Requires-Dist: seed-services-client (<1.0,>=0.31.0)
